LICENSE
README.md
setup.py
syz/__init__.py
syz/common.py
syz/test.py
syz.egg-info/PKG-INFO
syz.egg-info/SOURCES.txt
syz.egg-info/dependency_links.txt
syz.egg-info/requires.txt
syz.egg-info/top_level.txt