Metadata-Version: 2.1
Name: syz
Version: 0.1.0
Summary: common tools
Home-page: https://github.com/syz85/syz
Author: Sun YUANZHEN
Author-email: sunyuanzhen@gmail.com
Platform: any
Classifier: Programming Language :: Python :: 3
Classifier: License :: OSI Approved :: BSD License
Classifier: Operating System :: OS Independent
License-File: LICENSE
